{
  "count": 41,
  "data": [
    {
      "id": "60111965",
      "user": "nra4z-4itoo-odnhl-jpw4k-4bcvm-5tyf3-55yei-qfod6-4tnu3-erfmf-zqe",
      "token": "2dzg",
      "time": "2025-07-24T23:57:52.000Z",
      "buy": false,
      "amount_btc": 16483201,
      "amount_token": 927111409297191,
      "price": 1784,
      "bonded": true,
      "user_username": "拿住就好了",
      "user_image": null,
      "decimals": 3,
      "divisibility": 8
    },
    {
      "id": "60103947",
      "user": "ltqz5-wzehw-i3pre-e3bdn-i6ezp-za242-3dhtf-pc7ff-brbpm-xklbr-sqe",
      "token": "2dzg",
      "time": "2025-07-24T22:43:04.000Z",
      "buy": true,
      "amount_btc": 50000000,
      "amount_token": 2790412752594919,
      "price": 1788,
      "bonded": true,
      "user_username": "jssh",
      "user_image": "48921548-7165-4346-a3f2-4a09f5042ac5.jpg",
      "decimals": 3,
      "divisibility": 8
    },
    {
      "id": "60064737",
      "user": "o3ply-7xhoz-klskp-qgoos-vtumf-gdptt-nh6n2-37bgx-nixi3-6nwrb-xae",
      "token": "2dzg",
      "time": "2025-07-24T12:49:26.000Z",
      "buy": true,
      "amount_btc": 10129770,
      "amount_token": 567577316341435,
      "price": 1777,
      "bonded": true,
      "user_username": "peezy",
      "user_image": "08429885-1fab-4952-bb08-f744f371c92b.jpeg",
      "decimals": 3,
      "divisibility": 8
    },
    {
      "id": "60056665",
      "user": "lznu6-oecb5-ndmuq-uxplp-isif7-tlv3j-hcyli-43vsj-hettg-ukzcr-gae",
      "token": "2dzg",
      "time": "2025-07-24T11:35:29.000Z",
      "buy": true,
      "amount_btc": 44740399,
      "amount_token": 2515991779129447,
      "price": 1774,
      "bonded": true,
      "user_username": "砖石100U",
      "user_image": null,
      "decimals": 3,
      "divisibility": 8
    },
    {
      "id": "60020425",
      "user": "m7lqs-d2h74-sdrzs-fywpd-dhfoz-45lax-2veil-pthae-phsxu-jx5qh-3qe",
      "token": "2dzg",
      "time": "2025-07-24T07:37:11.000Z",
      "buy": true,
      "amount_btc": 50000000,
      "amount_token": 2829549985567886,
      "price": 1764,
      "bonded": true,
      "user_username": "lalalalala",
      "user_image": null,
      "decimals": 3,
      "divisibility": 8
    },
    {
      "id": "60020280",
      "user": "d5ynk-ngy6j-24m2d-cezex-gf7ke-vqdle-iezv3-t7jsj-5lzwv-puicj-dqe",
      "token": "2dzg",
      "time": "2025-07-24T07:35:34.000Z",
      "buy": true,
      "amount_btc": 10000000,
      "amount_token": 568175695422450,
      "price": 1752,
      "bonded": true,
      "user_username": "d5ynk-ngy6j",
      "user_image": null,
      "decimals": 3,
      "divisibility": 8
    },
    {
      "id": "60020269",
      "user": "gsnd4-fabxv-vawel-3fna4-exr4o-o4fih-pyolx-khflg-ynckf-z5rjt-qae",
      "token": "2dzg",
      "time": "2025-07-24T07:35:30.000Z",
      "buy": false,
      "amount_btc": 688174914,
      "amount_token": 37768066326444250,
      "price": 1750,
      "bonded": true,
      "user_username": "BYCBYC",
      "user_image": "7d2b10d4-a4dc-48bb-a69b-dc7197bd8e5e.jpg",
      "decimals": 3,
      "divisibility": 8
    },
    {
      "id": "60004118",
      "user": "bnwaj-ga3eo-n767n-xk6yw-rsc2o-ezfyz-xejwx-ept2a-t7mnh-lien7-pqe",
      "token": "2dzg",
      "time": "2025-07-24T05:53:13.000Z",
      "buy": false,
      "amount_btc": 17621578,
      "amount_token": 923204231487053,
      "price": 1916,
      "bonded": true,
      "user_username": "比特牛新人进场",
      "user_image": "2211a41d-6665-4ff4-ade8-eba21da5ff25.jpg",
      "decimals": 3,
      "divisibility": 8
    },
    {
      "id": "59993790",
      "user": "zo2rk-owks3-ecemw-gpgdq-tzbq7-igdzu-wiovc-paui3-jgqwx-646ol-zae",
      "token": "2dzg",
      "time": "2025-07-24T04:46:24.000Z",
      "buy": false,
      "amount_btc": 222329142,
      "amount_token": 11470590616661376,
      "price": 1920,
      "bonded": true,
      "user_username": "1tej5dh-owks",
      "user_image": null,
      "decimals": 3,
      "divisibility": 8
    },
    {
      "id": "60120122",
      "user": "ltqz5-wzehw-i3pre-e3bdn-i6ezp-za242-3dhtf-pc7ff-brbpm-xklbr-sqe",
      "token": "2dzg",
      "time": "2025-07-25T00:38:29.000Z",
      "buy": true,
      "amount_btc": 1000000,
      "amount_token": 55742390509673,
      "price": 1785,
      "bonded": true,
      "user_username": "jssh",
      "user_image": "48921548-7165-4346-a3f2-4a09f5042ac5.jpg",
      "decimals": 3,
      "divisibility": 8
    },
    {
      "id": "60124787",
      "user": "ltqz5-wzehw-i3pre-e3bdn-i6ezp-za242-3dhtf-pc7ff-brbpm-xklbr-sqe",
      "token": "2dzg",
      "time": "2025-07-25T01:19:55.000Z",
      "buy": false,
      "amount_btc": 53902893,
      "amount_token": 2846155143104592,
      "price": 1896,
      "bonded": true,
      "user_username": "jssh",
      "user_image": "48921548-7165-4346-a3f2-4a09f5042ac5.jpg",
      "decimals": 3,
      "divisibility": 8
    },
    {
      "id": "60124696",
      "user": "dm5cr-4lf2q-ogpsc-2k25w-mn5mv-tquo3-euvrl-otakq-gty5a-3tnfc-pae",
      "token": "2dzg",
      "time": "2025-07-25T01:19:20.000Z",
      "buy": false,
      "amount_btc": 148507999,
      "amount_token": 7740007787075659,
      "price": 1910,
      "bonded": true,
      "user_username": "woshinibaba",
      "user_image": null,
      "decimals": 3,
      "divisibility": 8
    },
    {
      "id": "60124563",
      "user": "dm5cr-4lf2q-ogpsc-2k25w-mn5mv-tquo3-euvrl-otakq-gty5a-3tnfc-pae",
      "token": "2dzg",
      "time": "2025-07-25T01:18:09.000Z",
      "buy": true,
      "amount_btc": 150000000,
      "amount_token": 7740007787075659,
      "price": 1946,
      "bonded": true,
      "user_username": "woshinibaba",
      "user_image": null,
      "decimals": 3,
      "divisibility": 8
    },
    {
      "id": "60124546",
      "user": "jhfnv-xmun3-5aoa5-7xdry-ak5uo-emtc5-pxqew-4yr7j-hziww-ugm73-bqe",
      "token": "2dzg",
      "time": "2025-07-25T01:17:55.000Z",
      "buy": true,
      "amount_btc": 10000000,
      "amount_token": 521275183571047,
      "price": 1909,
      "bonded": true,
      "user_username": "Dbly-uopb",
      "user_image": null,
      "decimals": 3,
      "divisibility": 8
    },
    {
      "id": "60124540",
      "user": "jzqve-iup4p-344e7-vfy6i-b7qkd-w2mol-6xi63-qibbq-ldunn-swcjo-cqe",
      "token": "2dzg",
      "time": "2025-07-25T01:17:52.000Z",
      "buy": true,
      "amount_btc": 150000000,
      "amount_token": 7900044975465087,
      "price": 1907,
      "bonded": true,
      "user_username": "anx.slaw 🌊",
      "user_image": "9e0e2f3b-dad3-4b31-bdb0-131e08e6f67c.jpg",
      "decimals": 3,
      "divisibility": 8
    },
    {
      "id": "60124534",
      "user": "rfgrj-qslrz-5uki6-p5vqc-exinf-ert2r-5c2dp-nqgd6-danth-omsqd-4ae",
      "token": "2dzg",
      "time": "2025-07-25T01:17:44.000Z",
      "buy": true,
      "amount_btc": 300000000,
      "amount_token": 16268679195211972,
      "price": 1871,
      "bonded": true,
      "user_username": "Llllllll",
      "user_image": null,
      "decimals": 3,
      "divisibility": 8
    },
    {
      "id": "60124528",
      "user": "jhfnv-xmun3-5aoa5-7xdry-ak5uo-emtc5-pxqew-4yr7j-hziww-ugm73-bqe",
      "token": "2dzg",
      "time": "2025-07-25T01:17:41.000Z",
      "buy": true,
      "amount_btc": 10000000,
      "amount_token": 553354773365653,
      "price": 1799,
      "bonded": true,
      "user_username": "Dbly-uopb",
      "user_image": null,
      "decimals": 3,
      "divisibility": 8
    },
    {
      "id": "60124522",
      "user": "jhfnv-xmun3-5aoa5-7xdry-ak5uo-emtc5-pxqew-4yr7j-hziww-ugm73-bqe",
      "token": "2dzg",
      "time": "2025-07-25T01:17:36.000Z",
      "buy": true,
      "amount_btc": 10000000,
      "amount_token": 554084750812009,
      "price": 1796,
      "bonded": true,
      "user_username": "Dbly-uopb",
      "user_image": null,
      "decimals": 3,
      "divisibility": 8
    },
    {
      "id": "60124506",
      "user": "jhfnv-xmun3-5aoa5-7xdry-ak5uo-emtc5-pxqew-4yr7j-hziww-ugm73-bqe",
      "token": "2dzg",
      "time": "2025-07-25T01:17:23.000Z",
      "buy": true,
      "amount_btc": 10000000,
      "amount_token": 554816174401638,
      "price": 1794,
      "bonded": true,
      "user_username": "Dbly-uopb",
      "user_image": null,
      "decimals": 3,
      "divisibility": 8
    },
    {
      "id": "60124500",
      "user": "jhfnv-xmun3-5aoa5-7xdry-ak5uo-emtc5-pxqew-4yr7j-hziww-ugm73-bqe",
      "token": "2dzg",
      "time": "2025-07-25T01:17:19.000Z",
      "buy": true,
      "amount_btc": 10000000,
      "amount_token": 555549047957923,
      "price": 1792,
      "bonded": true,
      "user_username": "Dbly-uopb",
      "user_image": null,
      "decimals": 3,
      "divisibility": 8
    },
    {
      "id": "60124489",
      "user": "jhfnv-xmun3-5aoa5-7xdry-ak5uo-emtc5-pxqew-4yr7j-hziww-ugm73-bqe",
      "token": "2dzg",
      "time": "2025-07-25T01:17:14.000Z",
      "buy": true,
      "amount_btc": 10000000,
      "amount_token": 556283375316896,
      "price": 1789,
      "bonded": true,
      "user_username": "Dbly-uopb",
      "user_image": null,
      "decimals": 3,
      "divisibility": 8
    },
    {
      "id": "60124478",
      "user": "jhfnv-xmun3-5aoa5-7xdry-ak5uo-emtc5-pxqew-4yr7j-hziww-ugm73-bqe",
      "token": "2dzg",
      "time": "2025-07-25T01:17:10.000Z",
      "buy": true,
      "amount_btc": 10000000,
      "amount_token": 557019160327284,
      "price": 1787,
      "bonded": true,
      "user_username": "Dbly-uopb",
      "user_image": null,
      "decimals": 3,
      "divisibility": 8
    },
    {
      "id": "60124952",
      "user": "uzbnm-k2zuw-wv3x7-amfil-jiffx-yylen-jx3qz-uqwot-a2f55-2ludt-qqe",
      "token": "2dzg",
      "time": "2025-07-25T01:21:57.000Z",
      "buy": true,
      "amount_btc": 5000000,
      "amount_token": 269895428196590,
      "price": 1843,
      "bonded": true,
      "user_username": "BABYODIN铁军- X小赢家",
      "user_image": "d8f45cc0-9324-4194-a9c7-6b3fddd0b9ca.jpg",
      "decimals": 3,
      "divisibility": 8
    },
    {
      "id": "60124883",
      "user": "ntxic-niq5h-lb2oz-u7dob-jlds4-6pqbt-fzzfm-o2wze-s4cny-feknn-lqe",
      "token": "2dzg",
      "time": "2025-07-25T01:21:08.000Z",
      "buy": true,
      "amount_btc": 50000000,
      "amount_token": 2708659737530433,
      "price": 1842,
      "bonded": true,
      "user_username": "beautiful",
      "user_image": null,
      "decimals": 3,
      "divisibility": 8
    },
    {
      "id": "60124877",
      "user": "uzbnm-k2zuw-wv3x7-amfil-jiffx-yylen-jx3qz-uqwot-a2f55-2ludt-qqe",
      "token": "2dzg",
      "time": "2025-07-25T01:21:04.000Z",
      "buy": true,
      "amount_btc": 30000000,
      "amount_token": 1633699550027003,
      "price": 1830,
      "bonded": true,
      "user_username": "BABYODIN铁军- X小赢家",
      "user_image": "d8f45cc0-9324-4194-a9c7-6b3fddd0b9ca.jpg",
      "decimals": 3,
      "divisibility": 8
    },
    {
      "id": "60124824",
      "user": "rfgrj-qslrz-5uki6-p5vqc-exinf-ert2r-5c2dp-nqgd6-danth-omsqd-4ae",
      "token": "2dzg",
      "time": "2025-07-25T01:20:18.000Z",
      "buy": false,
      "amount_btc": 301057199,
      "amount_token": 16268679195211972,
      "price": 1823,
      "bonded": true,
      "user_username": "Llllllll",
      "user_image": null,
      "decimals": 3,
      "divisibility": 8
    },
    {
      "id": "60126012",
      "user": "jzqve-iup4p-344e7-vfy6i-b7qkd-w2mol-6xi63-qibbq-ldunn-swcjo-cqe",
      "token": "2dzg",
      "time": "2025-07-25T01:38:51.000Z",
      "buy": false,
      "amount_btc": 143575522,
      "amount_token": 7900044975465087,
      "price": 1809,
      "bonded": true,
      "user_username": "anx.slaw 🌊",
      "user_image": "9e0e2f3b-dad3-4b31-bdb0-131e08e6f67c.jpg",
      "decimals": 3,
      "divisibility": 8
    },
    {
      "id": "60127415",
      "user": "jhfnv-xmun3-5aoa5-7xdry-ak5uo-emtc5-pxqew-4yr7j-hziww-ugm73-bqe",
      "token": "2dzg",
      "time": "2025-07-25T01:51:34.000Z",
      "buy": true,
      "amount_btc": 10000000,
      "amount_token": 549573814472583,
      "price": 1811,
      "bonded": true,
      "user_username": "Dbly-uopb",
      "user_image": null,
      "decimals": 3,
      "divisibility": 8
    },
    {
      "id": "60128035",
      "user": "vmjtv-j7f6m-4hy53-e37tf-vpffu-jd3ic-ivxvm-bbk46-fuxkg-mo4mj-zae",
      "token": "2dzg",
      "time": "2025-07-25T01:56:31.000Z",
      "buy": true,
      "amount_btc": 10000000,
      "amount_token": 548133134131964,
      "price": 1816,
      "bonded": true,
      "user_username": "BITFI 群328715832",
      "user_image": "53e955a8-753f-4165-83d0-42516a61baf8.jpg",
      "decimals": 3,
      "divisibility": 8
    },
    {
      "id": "60128015",
      "user": "jhfnv-xmun3-5aoa5-7xdry-ak5uo-emtc5-pxqew-4yr7j-hziww-ugm73-bqe",
      "token": "2dzg",
      "time": "2025-07-25T01:56:22.000Z",
      "buy": true,
      "amount_btc": 10000000,
      "amount_token": 548852764890961,
      "price": 1814,
      "bonded": true,
      "user_username": "Dbly-uopb",
      "user_image": null,
      "decimals": 3,
      "divisibility": 8
    },
    {
      "id": "60136872",
      "user": "vmjtv-j7f6m-4hy53-e37tf-vpffu-jd3ic-ivxvm-bbk46-fuxkg-mo4mj-zae",
      "token": "2dzg",
      "time": "2025-07-25T02:54:28.000Z",
      "buy": false,
      "amount_btc": 9900270,
      "amount_token": 548133134131964,
      "price": 1814,
      "bonded": true,
      "user_username": "BITFI 群328715832",
      "user_image": "53e955a8-753f-4165-83d0-42516a61baf8.jpg",
      "decimals": 3,
      "divisibility": 8
    },
    {
      "id": "60139109",
      "user": "nra4z-4itoo-odnhl-jpw4k-4bcvm-5tyf3-55yei-qfod6-4tnu3-erfmf-zqe",
      "token": "2dzg",
      "time": "2025-07-25T02:58:28.000Z",
      "buy": false,
      "amount_btc": 5576052,
      "amount_token": 309037136432397,
      "price": 1812,
      "bonded": true,
      "user_username": "拿住就好了",
      "user_image": null,
      "decimals": 3,
      "divisibility": 8
    },
    {
      "id": "60143411",
      "user": "za737-fqvyz-utafh-gb6ab-is2aa-uq3wq-owti2-d26df-wgtrq-iib3n-sqe",
      "token": "2dzg",
      "time": "2025-07-25T03:13:28.000Z",
      "buy": false,
      "amount_btc": 128303302,
      "amount_token": 7174405690706108,
      "price": 1782,
      "bonded": true,
      "user_username": "love.ll",
      "user_image": null,
      "decimals": 3,
      "divisibility": 8
    },
    {
      "id": "60150869",
      "user": "4fb3s-rg3lj-untra-3e3m4-fd22y-ntkiz-mqz4w-s46nc-psgjg-5fqb5-4ae",
      "token": "2dzg",
      "time": "2025-07-25T03:59:35.000Z",
      "buy": false,
      "amount_btc": 1788284,
      "amount_token": 100852316090882,
      "price": 1781,
      "bonded": true,
      "user_username": "After Spring",
      "user_image": null,
      "decimals": 3,
      "divisibility": 8
    },
    {
      "id": "60150855",
      "user": "4fb3s-rg3lj-untra-3e3m4-fd22y-ntkiz-mqz4w-s46nc-psgjg-5fqb5-4ae",
      "token": "2dzg",
      "time": "2025-07-25T03:59:28.000Z",
      "buy": true,
      "amount_btc": 1000000,
      "amount_token": 55830693043520,
      "price": 1782,
      "bonded": true,
      "user_username": "After Spring",
      "user_image": null,
      "decimals": 3,
      "divisibility": 8
    },
    {
      "id": "60151486",
      "user": "ntxic-niq5h-lb2oz-u7dob-jlds4-6pqbt-fzzfm-o2wze-s4cny-feknn-lqe",
      "token": "2dzg",
      "time": "2025-07-25T04:03:52.000Z",
      "buy": false,
      "amount_btc": 47869906,
      "amount_token": 2708659737530433,
      "price": 1770,
      "bonded": true,
      "user_username": "beautiful",
      "user_image": null,
      "decimals": 3,
      "divisibility": 8
    },
    {
      "id": "60172519",
      "user": "rfgrj-qslrz-5uki6-p5vqc-exinf-ert2r-5c2dp-nqgd6-danth-omsqd-4ae",
      "token": "2dzg",
      "time": "2025-07-25T06:39:52.000Z",
      "buy": true,
      "amount_btc": 300000000,
      "amount_token": 15897529679959936,
      "price": 1914,
      "bonded": true,
      "user_username": "Llllllll",
      "user_image": null,
      "decimals": 3,
      "divisibility": 8
    },
    {
      "id": "60172347",
      "user": "rfgrj-qslrz-5uki6-p5vqc-exinf-ert2r-5c2dp-nqgd6-danth-omsqd-4ae",
      "token": "2dzg",
      "time": "2025-07-25T06:38:37.000Z",
      "buy": true,
      "amount_btc": 300000000,
      "amount_token": 16530919408682528,
      "price": 1841,
      "bonded": true,
      "user_username": "Llllllll",
      "user_image": null,
      "decimals": 3,
      "divisibility": 8
    },
    {
      "id": "60173522",
      "user": "rfgrj-qslrz-5uki6-p5vqc-exinf-ert2r-5c2dp-nqgd6-danth-omsqd-4ae",
      "token": "2dzg",
      "time": "2025-07-25T06:47:36.000Z",
      "buy": false,
      "amount_btc": 594066728,
      "amount_token": 32428449088642464,
      "price": 1770,
      "bonded": true,
      "user_username": "Llllllll",
      "user_image": null,
      "decimals": 3,
      "divisibility": 8
    },
    {
      "id": "60192729",
      "user": "bs2fp-v4ktr-cfb3k-tm3vm-itzcv-7nz54-gi7gs-pwq7s-qpnwq-wv77b-vae",
      "token": "2dzg",
      "time": "2025-07-25T08:15:57.000Z",
      "buy": false,
      "amount_btc": 182722626,
      "amount_token": 10500000000000000,
      "price": 1727,
      "bonded": true,
      "user_username": "ICBin ∞",
      "user_image": "24af5a68-6087-4913-ab1e-71e522a6360c.png",
      "decimals": 3,
      "divisibility": 8
    },
    {
      "id": "60222252",
      "user": "m7lqs-d2h74-sdrzs-fywpd-dhfoz-45lax-2veil-pthae-phsxu-jx5qh-3qe",
      "token": "2dzg",
      "time": "2025-07-25T11:44:23.000Z",
      "buy": false,
      "amount_btc": 48477298,
      "amount_token": 2829549985567886,
      "price": 1716,
      "bonded": true,
      "user_username": "lalalalala",
      "user_image": null,
      "decimals": 3,
      "divisibility": 8
    }
  ]
}