{
  "count": 20,
  "data": [
    {
      "id": "51219016",
      "user": "aovmm-dichc-yrwv7-d3gvk-gj4uz-5e2mb-d7jap-szvqd-subgo-6mmpz-sqe",
      "token": "2dzg",
      "time": "2025-06-28T16:07:15.000Z",
      "buy": false,
      "amount_btc": 95900014,
      "amount_token": 6953501398735879,
      "price": 1376,
      "bonded": true,
      "user_username": "=-=",
      "user_image": null,
      "decimals": 3,
      "divisibility": 8
    },
    {
      "id": "51149563",
      "user": "eiqwp-ujakd-oxg6z-v3l6a-jwnuu-zf462-7rrli-6ztau-ukaz6-mrpn4-jqe",
      "token": "2dzg",
      "time": "2025-06-28T10:53:39.000Z",
      "buy": true,
      "amount_btc": 1000000,
      "amount_token": 71307831488401,
      "price": 1395,
      "bonded": true,
      "user_username": "2gfc＿w1fc盛",
      "user_image": null,
      "decimals": 3,
      "divisibility": 8
    },
    {
      "id": "51122991",
      "user": "iyzuc-hfqud-yo4fl-7mr6a-engxz-7zxd7-fuudo-m3rhp-n5czp-ul73r-nae",
      "token": "2dzg",
      "time": "2025-06-28T06:49:40.000Z",
      "buy": false,
      "amount_btc": 125970317,
      "amount_token": 8994676145634454,
      "price": 1395,
      "bonded": true,
      "user_username": "Yoo7",
      "user_image": "2456d22d-09c9-4f0a-89e9-b725540082ba.jpeg",
      "decimals": 3,
      "divisibility": 8
    },
    {
      "id": "51111941",
      "user": "senl2-cmcnw-uzqs7-iente-wtuim-mzfvb-mspy5-vehf2-5x36b-mcl5k-gqe",
      "token": "2dzg",
      "time": "2025-06-28T04:57:52.000Z",
      "buy": false,
      "amount_btc": 105788425,
      "amount_token": 7433187515074261,
      "price": 1419,
      "bonded": true,
      "user_username": "Gbkih",
      "user_image": null,
      "decimals": 3,
      "divisibility": 8
    },
    {
      "id": "51111760",
      "user": "3veia-wz2rm-g4hsd-jtdtv-yltmt-442xm-4ep66-ptqyk-jzfik-23eg3-2qe",
      "token": "2dzg",
      "time": "2025-06-28T04:56:37.000Z",
      "buy": false,
      "amount_btc": 156209245,
      "amount_token": 10780305194659240,
      "price": 1440,
      "bonded": true,
      "user_username": "如来神鞭",
      "user_image": "b6594746-f301-4295-8e9d-597348d29d1a.png",
      "decimals": 3,
      "divisibility": 8
    },
    {
      "id": "51094994",
      "user": "eiqwp-ujakd-oxg6z-v3l6a-jwnuu-zf462-7rrli-6ztau-ukaz6-mrpn4-jqe",
      "token": "2dzg",
      "time": "2025-06-28T02:08:33.000Z",
      "buy": true,
      "amount_btc": 20000000,
      "amount_token": 1353760406810162,
      "price": 1471,
      "bonded": true,
      "user_username": "2gfc＿w1fc盛",
      "user_image": null,
      "decimals": 3,
      "divisibility": 8
    },
    {
      "id": "51094957",
      "user": "eiqwp-ujakd-oxg6z-v3l6a-jwnuu-zf462-7rrli-6ztau-ukaz6-mrpn4-jqe",
      "token": "2dzg",
      "time": "2025-06-28T02:08:06.000Z",
      "buy": true,
      "amount_btc": 10000000,
      "amount_token": 678254024029937,
      "price": 1467,
      "bonded": true,
      "user_username": "2gfc＿w1fc盛",
      "user_image": null,
      "decimals": 3,
      "divisibility": 8
    },
    {
      "id": "51094889",
      "user": "eiqwp-ujakd-oxg6z-v3l6a-jwnuu-zf462-7rrli-6ztau-ukaz6-mrpn4-jqe",
      "token": "2dzg",
      "time": "2025-06-28T02:07:40.000Z",
      "buy": true,
      "amount_btc": 60000000,
      "amount_token": 4088905910797497,
      "price": 1465,
      "bonded": true,
      "user_username": "2gfc＿w1fc盛",
      "user_image": null,
      "decimals": 3,
      "divisibility": 8
    },
    {
      "id": "51094854",
      "user": "eiqwp-ujakd-oxg6z-v3l6a-jwnuu-zf462-7rrli-6ztau-ukaz6-mrpn4-jqe",
      "token": "2dzg",
      "time": "2025-06-28T02:07:26.000Z",
      "buy": true,
      "amount_btc": 60000000,
      "amount_token": 4122390938323636,
      "price": 1454,
      "bonded": true,
      "user_username": "2gfc＿w1fc盛",
      "user_image": null,
      "decimals": 3,
      "divisibility": 8
    },
    {
      "id": "51316034",
      "user": "qhm2k-oz3bc-uem7s-65bml-3l2iv-pobtw-siux3-kkrkd-umalg-ww5fs-zqe",
      "token": "2dzg",
      "time": "2025-06-29T09:49:16.000Z",
      "buy": false,
      "amount_btc": 291643068,
      "amount_token": 21988012691345772,
      "price": 1305,
      "bonded": true,
      "user_username": "Valhalla社区",
      "user_image": null,
      "decimals": 3,
      "divisibility": 8
    },
    {
      "id": "51315976",
      "user": "qhm2k-oz3bc-uem7s-65bml-3l2iv-pobtw-siux3-kkrkd-umalg-ww5fs-zqe",
      "token": "2dzg",
      "time": "2025-06-29T09:48:58.000Z",
      "buy": false,
      "amount_btc": 81730840,
      "amount_token": 6000000000000000,
      "price": 1361,
      "bonded": true,
      "user_username": "Valhalla社区",
      "user_image": null,
      "decimals": 3,
      "divisibility": 8
    },
    {
      "id": "51321798",
      "user": "v6ltb-cuvgf-4iz7e-eqbh2-xy43y-ppdvb-yddz2-pgbcl-5ydje-ochox-eqe",
      "token": "2dzg",
      "time": "2025-06-29T10:27:27.000Z",
      "buy": false,
      "amount_btc": 242485542,
      "amount_token": 19000000000000000,
      "price": 1260,
      "bonded": true,
      "user_username": "v1ltb-cuvgf",
      "user_image": null,
      "decimals": 3,
      "divisibility": 8
    },
    {
      "id": "51388528",
      "user": "lme4s-nxtnh-47uef-gfqan-bei23-wroj2-3zabo-v7uin-c5drm-taniy-pqe",
      "token": "2dzg",
      "time": "2025-06-29T20:02:34.000Z",
      "buy": false,
      "amount_btc": 168308197,
      "amount_token": 13258007816994376,
      "price": 1260,
      "bonded": true,
      "user_username": "符文帮符文",
      "user_image": null,
      "decimals": 3,
      "divisibility": 8
    },
    {
      "id": "51388491",
      "user": "lme4s-nxtnh-47uef-gfqan-bei23-wroj2-3zabo-v7uin-c5drm-taniy-pqe",
      "token": "2dzg",
      "time": "2025-06-29T20:01:24.000Z",
      "buy": true,
      "amount_btc": 50000000,
      "amount_token": 3865555168728036,
      "price": 1291,
      "bonded": true,
      "user_username": "符文帮符文",
      "user_image": null,
      "decimals": 3,
      "divisibility": 8
    },
    {
      "id": "51388465",
      "user": "lme4s-nxtnh-47uef-gfqan-bei23-wroj2-3zabo-v7uin-c5drm-taniy-pqe",
      "token": "2dzg",
      "time": "2025-06-29T20:01:09.000Z",
      "buy": true,
      "amount_btc": 50000000,
      "amount_token": 3893629073993761,
      "price": 1282,
      "bonded": true,
      "user_username": "符文帮符文",
      "user_image": null,
      "decimals": 3,
      "divisibility": 8
    },
    {
      "id": "51388454",
      "user": "lme4s-nxtnh-47uef-gfqan-bei23-wroj2-3zabo-v7uin-c5drm-taniy-pqe",
      "token": "2dzg",
      "time": "2025-06-29T20:01:04.000Z",
      "buy": true,
      "amount_btc": 10000000,
      "amount_token": 782118212320886,
      "price": 1273,
      "bonded": true,
      "user_username": "符文帮符文",
      "user_image": null,
      "decimals": 3,
      "divisibility": 8
    },
    {
      "id": "51388444",
      "user": "lme4s-nxtnh-47uef-gfqan-bei23-wroj2-3zabo-v7uin-c5drm-taniy-pqe",
      "token": "2dzg",
      "time": "2025-06-29T20:01:00.000Z",
      "buy": true,
      "amount_btc": 10000000,
      "amount_token": 783255906609997,
      "price": 1271,
      "bonded": true,
      "user_username": "符文帮符文",
      "user_image": null,
      "decimals": 3,
      "divisibility": 8
    },
    {
      "id": "51388438",
      "user": "lme4s-nxtnh-47uef-gfqan-bei23-wroj2-3zabo-v7uin-c5drm-taniy-pqe",
      "token": "2dzg",
      "time": "2025-06-29T20:00:59.000Z",
      "buy": true,
      "amount_btc": 50000000,
      "amount_token": 3933449455341695,
      "price": 1269,
      "bonded": true,
      "user_username": "符文帮符文",
      "user_image": null,
      "decimals": 3,
      "divisibility": 8
    },
    {
      "id": "51397023",
      "user": "ygugc-ix7ws-22zms-i64kh-sjszn-y4rbz-6jrgq-y65rh-eyrto-zfu4q-rqe",
      "token": "2dzg",
      "time": "2025-06-29T23:07:00.000Z",
      "buy": false,
      "amount_btc": 68356303,
      "amount_token": 5478730517904042,
      "price": 1247,
      "bonded": true,
      "user_username": "NeoLiang",
      "user_image": null,
      "decimals": 3,
      "divisibility": 8
    },
    {
      "id": "51397709",
      "user": "eiqwp-ujakd-oxg6z-v3l6a-jwnuu-zf462-7rrli-6ztau-ukaz6-mrpn4-jqe",
      "token": "2dzg",
      "time": "2025-06-29T23:21:11.000Z",
      "buy": false,
      "amount_btc": 126844051,
      "amount_token": 10314619111449632,
      "price": 1224,
      "bonded": true,
      "user_username": "2ufc＿w1fc盛",
      "user_image": null,
      "decimals": 3,
      "divisibility": 8
    }
  ]
}